[
    {
        "id": 1,
        "nombre": "TORREON 1 LAGUNA SUR #1450"
    },
    {
        "id": 2,
        "nombre": "TORREON 2 ALLENDE #205 OTE."
    },
    {
        "id": 3,
        "nombre": "TORREON 3 ALLENDE #205 OTE."
    },
    {
        "id": 4,
        "nombre": "FLOR DE JIMULCO"
    },
    {
        "id": 5,
        "nombre": "LA JOYA"
    },
    {
        "id": 6,
        "nombre": "TORREON BLVR. REV. #399 OTE."
    },
    {
        "id": 7,
        "nombre": "TORREON BLVR. REV. #1953 OTE."
    },
    {
        "id": 8,
        "nombre": "TORREON REV. #409-A PONIENTE"
    },
    {
        "id": 9,
        "nombre": "EJ. LA CONCHA"
    },
    {
        "id": 10,
        "nombre": "EJ. LA PAZ"
    },
    {
        "id": 11,
        "nombre": "TORREON"
    },
    {
        "id": 12,
        "nombre": "TORREON"
    },
    {
        "id": 13,
        "nombre": "TORREON"
    },
    {
        "id": 14,
        "nombre": "TORREON"
    },
    {
        "id": 15,
        "nombre": "TORREON"
    },
    {
        "id": 16,
        "nombre": "TORREON"
    },
    {
        "id": 17,
        "nombre": "TORREON"
    },
    {
        "id": 18,
        "nombre": "TORREON"
    },
    {
        "id": 19,
        "nombre": "TORREON"
    },
    {
        "id": 22,
        "nombre": "TORREON"
    },
    {
        "id": 23,
        "nombre": "TORREON"
    },
    {
        "id": 24,
        "nombre": "TORREON"
    },
    {
        "id": 26,
        "nombre": "TORREON"
    },
    {
        "id": 27,
        "nombre": "TORREON"
    },
    {
        "id": 28,
        "nombre": "TORREON"
    }
]